{
  "tags": [
    "nomlex1",
    "verblex1",
    "auslex",
    "doublehnd",
    "sym",
    "para",
    "obscure",
    "engtf1",
    "engtf2",
    "syn1",
    "syn2",
    "syn3"
  ],
  "sense": "",
  "blend": "",
  "queries": "",
  "genmean": "",
  "questlex": [],
  "idgloss": "beg.3",
  "oldentry": "Popular explanation: assuming the stance of a begging dog.",
  "english": [
    "dog",
    "beg"
  ],
  "deictic": [],
  "verblex": [
    "1. Of a dog, to sit on your hind legs and raise your forelegs. English = beg."
  ],
  "cf": [],
  "interj": [],
  "partlex": [],
  "nomlex": [
    "1. An animal that is often kept as a pet or used to guard or hunt things. English = dog."
  ],
  "signNumber": 3934,
  "recordNumber": 2345,
  "signVisualComposition": "",
  "activeHandShape": 5.3,
  "passiveHandShape": 5.3,
  "primaryLocation": 15,
  "secondLocation": 26,
  "antonyms": [],
  "synonyms": [
    "dog.1",
    "dog.2"
  ]
}
