{
  "tags": [
    "nomlex1",
    "nomlex2",
    "reglex",
    "nth",
    "doublehnd",
    "sym",
    "engtf1",
    "cf1",
    "syn1",
    "syn2",
    "syn3"
  ],
  "sense": "",
  "blend": "",
  "queries": "",
  "english": [
    "birthday"
  ],
  "deictic": [],
  "cf": [
    "birthday.5"
  ],
  "signNumber": 3754,
  "recordNumber": 2217,
  "signVisualComposition": "",
  "activeHandShape": 5.3,
  "passiveHandShape": 5.3,
  "primaryLocation": 15,
  "secondLocation": 27,
  "antonyms": [],
  "synonyms": [
    "birthday.1",
    "birthday.3",
    "birthday.4"
  ],
  "interjection": [],
  "particleLexeme": [],
  "verbLexeme": [],
  "questionLexeme": [],
  "genitiveClassifiers": "",
  "nominalLexeme": [
    "1. The anniversary of the date on which you were born. English = birthday.",
    "2. A celebration of the anniversary of the date on which you were born. English = birthday party."
  ],
  "idGloss": "birthday.2",
  "oldEntry": ""
}
