{
  "tags": [
    "nomlex1",
    "verblex1",
    "auslex",
    "clothes",
    "onehand",
    "obscure",
    "engtf1"
  ],
  "sense": "",
  "blend": "",
  "queries": "",
  "english": [
    "brooch"
  ],
  "deictic": [],
  "cf": [],
  "signNumber": 5134,
  "recordNumber": 3100,
  "signVisualComposition": "",
  "activeHandshape": 7.1,
  "passiveHandshape": 0,
  "primaryLocation": 14,
  "secondLocation": null,
  "antonyms": [],
  "synonyms": [],
  "interjection": [],
  "particleLexeme": [],
  "verbLexeme": [
    "1. To pin a brooch onto a dress or a blouse."
  ],
  "questionLexeme": [],
  "generalMeaning": "",
  "nominalLexeme": [
    "1. A small piece of jewellery with a pin at the back. You attach it to a dress or a blouse. English = brooch."
  ],
  "idGloss": "brooch",
  "oldEntry": "Popular explanation: pining on a brooch."
}
