{
  "tags": [
    "nomlex1",
    "nomlex2",
    "auslex",
    "family",
    "doublehnd",
    "alternate",
    "sym",
    "opaque",
    "engtf1",
    "ant1",
    "syn1"
  ],
  "sense": "",
  "blend": "",
  "queries": "",
  "english": [
    "brother"
  ],
  "deictic": [],
  "cf": [],
  "signNumber": 5789,
  "recordNumber": 3433,
  "signVisualComposition": "",
  "activeHandshape": 10.1,
  "passiveHandshape": 10.1,
  "primaryLocation": 15,
  "secondLocation": 25,
  "antonyms": [
    "sister"
  ],
  "synonyms": [],
  "interjection": [],
  "particleLexeme": [],
  "verbLexeme": [],
  "questionLexeme": [],
  "generalMeaning": "",
  "nominalLexeme": [
    "1. A boy or a man who has the same parents as you. English = brother.",
    "2. A title given to a man who belongs to a religious institution such as a monastery. English = brother."
  ],
  "idGloss": "brother.1a",
  "oldEntry": ""
}
