{
  "tags": [
    "nomlex1",
    "verblex1",
    "auslex",
    "doublehnd",
    "sym",
    "transl",
    "engtf1"
  ],
  "sense": "",
  "blend": "",
  "queries": "",
  "genmean": "",
  "questlex": [],
  "idgloss": "bundle",
  "oldentry": "Popular explanation: gathering a bundle together.",
  "english": [
    "bundle"
  ],
  "deictic": [],
  "verblex": [
    "1. To tie a number of things together or wrap them in cloth so that they can be carried or stored. English = bundle."
  ],
  "cf": [],
  "interj": [],
  "partlex": [],
  "nomlex": [
    "1. A number of things tied together or wrapped in a cloth so that they can be carried or stored. English = bundle."
  ],
  "signNumber": 4630,
  "recordNumber": 2805,
  "signVisualComposition": "",
  "activeHandShape": 5.5,
  "passiveHandShape": 5.5,
  "primaryLocation": 15,
  "secondLocation": 26,
  "antonyms": [],
  "synonyms": []
}
