{
  "tags": [
    "nomlex1",
    "gensign",
    "sports",
    "doublehnd",
    "para",
    "transl",
    "engtf1"
  ],
  "sense": null,
  "blend": null,
  "queries": null,
  "english": [
    "caddie"
  ],
  "deictic": [],
  "signNumber": 5841,
  "recordNumber": 3474,
  "signVisualComposition": null,
  "activeHandshape": 10.1,
  "passiveHandshape": 10.1,
  "primaryLocation": 13,
  "secondLocation": 26,
  "antonyms": [],
  "synonyms": [],
  "interjection": [],
  "particleLexeme": [],
  "verbLexeme": [],
  "questionLexeme": [],
  "generalMeaning": "The act of carrying something heavy slung over your shoulder, or any object or action directly or indirectly associated with this, especially a caddie.",
  "nominalLexeme": [
    "1. A person who carries a bag of golf clubs. English = caddie."
  ],
  "idGloss": "caddie",
  "oldEntry": "Popular explanation: carrying a golf bag over the shoulder.",
  "seeAlso": []
}
