{
  "tags": [
    "verblex1",
    "verblex2",
    "auslex",
    "judge",
    "people",
    "onehand",
    "opaque",
    "engtf1",
    "engtf2",
    "engtf3",
    "cf1"
  ],
  "sense": "",
  "blend": "",
  "queries": "",
  "genmean": "",
  "questlex": [],
  "idgloss": "choosy",
  "oldentry": "",
  "english": [
    "indecisive",
    "choosy",
    "fastidious"
  ],
  "deictic": [],
  "verblex": [
    "1. Of a person, to find it not easy to make decisions or choices. English = (be) indecisive.",
    "2. Of a person, to be difficult to please, because they will only accept something if it is exactly what they want. English = (be) choosy, (be) fastidious."
  ],
  "cf": [
    "which.1a"
  ],
  "interj": [],
  "partlex": [],
  "nomlex": [],
  "signNumber": 6610,
  "recordNumber": 3933,
  "signVisualComposition": "",
  "activeHandShape": 15.1,
  "passiveHandShape": 0,
  "primaryLocation": 15,
  "secondLocation": null,
  "antonyms": [],
  "synonyms": []
}
