{
  "tags": [
    "nomlex1",
    "nomlex2",
    "verblex1",
    "restrict",
    "arts",
    "twohand",
    "domonly",
    "engtf1",
    "engtf2",
    "engtf3"
  ],
  "sense": null,
  "blend": null,
  "queries": null,
  "english": [
    "choreography",
    "choreographer",
    "choreograph"
  ],
  "deictic": [],
  "signNumber": 4687,
  "recordNumber": 2831,
  "signVisualComposition": null,
  "activeHandshape": 5.5,
  "passiveHandshape": 5.3,
  "primaryLocation": 14,
  "secondLocation": 25,
  "antonyms": [],
  "synonyms": [],
  "interjection": [],
  "particleLexeme": [],
  "verbLexeme": [
    "1. To invent the steps and movements of ballets or other dances, and tell the dancers how to perform them. English = choreograph."
  ],
  "questionLexeme": [],
  "generalMeaning": null,
  "nominalLexeme": [
    "1. The art of inventing the steps and movements of ballets or other dances. English = choreography.",
    "2. A person whose job it is to invent the steps and movements of ballets or other dances. English = choreographer."
  ],
  "idGloss": "choreographer",
  "oldEntry": null,
  "seeAlso": []
}
