{
  "tags": [
    "nomlex1",
    "auslex",
    "twohand",
    "domonly",
    "telecommun",
    "engtf1"
  ],
  "sense": "",
  "blend": "",
  "queries": "",
  "genmean": "",
  "questlex": [],
  "idgloss": "computer.2",
  "oldentry": "",
  "english": [
    "computer"
  ],
  "deictic": [],
  "verblex": [],
  "cf": [],
  "interj": [],
  "partlex": [],
  "nomlex": [
    "1. An electronic machine that can quickly make calculations, store, rearrange, and retrieve information, or control another machine. English = computer."
  ],
  "signNumber": 4688,
  "recordNumber": 2832,
  "signVisualComposition": "",
  "activeHandShape": 5.5,
  "passiveHandShape": 5.3,
  "primaryLocation": 14,
  "secondLocation": 25,
  "antonyms": [],
  "synonyms": []
}
