{
  "tags": [
    "nomlex1",
    "nomlex2",
    "verblex1",
    "auslex",
    "autos",
    "twohand",
    "domonly",
    "engtf1",
    "syn1"
  ],
  "sense": "",
  "blend": "",
  "queries": "",
  "genmean": "",
  "questlex": [],
  "idgloss": "crane.1a",
  "oldentry": "",
  "english": [
    "crane"
  ],
  "deictic": [],
  "verblex": [
    "1. To lift or move something using a crane."
  ],
  "cf": [],
  "interj": [],
  "partlex": [],
  "nomlex": [
    "1. A large machine that moves heavy things by lifting them in the air. English = crane."
  ],
  "signNumber": 1503,
  "recordNumber": 895,
  "signVisualComposition": "",
  "activeHandShape": 1.2,
  "passiveHandShape": 5.3,
  "primaryLocation": 15,
  "secondLocation": 20,
  "antonyms": [],
  "synonyms": []
}
