{
  "tags": [
    "nomlex1",
    "auslex",
    "work",
    "doublehnd",
    "sym",
    "engtf1",
    "cf1",
    "cf2",
    "syn1"
  ],
  "sense": "2",
  "blend": null,
  "queries": null,
  "english": [
    "factory"
  ],
  "deictic": [],
  "signNumber": 4844,
  "recordNumber": 2927,
  "signVisualComposition": null,
  "activeHandshape": 6.1,
  "passiveHandshape": 6.1,
  "primaryLocation": 15,
  "secondLocation": 25,
  "antonyms": [],
  "synonyms": [
    "factory.1"
  ],
  "interjection": [],
  "particleLexeme": [],
  "verbLexeme": [],
  "questionLexeme": [],
  "generalMeaning": null,
  "nominalLexeme": [
    "1. A large building or a group of buildings where machines are used to make goods in large quantities. English = factory."
  ],
  "idGloss": "factory.2",
  "oldEntry": null,
  "seeAlso": [
    "broad.1a",
    "tall.2"
  ]
}
