{
  "tags": [
    "init",
    "nomlex1",
    "auslex",
    "family",
    "doublehnd",
    "sym",
    "engtf1",
    "syn1",
    "syn2"
  ],
  "sense": "",
  "blend": "FAMILY + F",
  "queries": "",
  "english": [
    "family"
  ],
  "deictic": [],
  "cf": [],
  "signNumber": 2070,
  "recordNumber": 1207,
  "signVisualComposition": "",
  "activeHandShape": 2.4,
  "passiveHandShape": 2.4,
  "primaryLocation": 14,
  "secondLocation": 24,
  "antonyms": [],
  "synonyms": [
    "family.1"
  ],
  "interjection": [],
  "particleLexeme": [],
  "verbLexeme": [],
  "questionLexeme": [],
  "genitiveClassifiers": "",
  "nominalLexeme": [
    "1. A group of people who are related to each other, especially parents and their children. English = family."
  ],
  "idGloss": "family.2a",
  "oldEntry": ""
}
