{
  "tags": [
    "nomlex1",
    "verblex1",
    "auslex",
    "twohand",
    "domonly",
    "obscure",
    "law",
    "engtf1"
  ],
  "sense": null,
  "blend": null,
  "queries": null,
  "english": [
    "fingerprint"
  ],
  "deictic": [],
  "signNumber": 6548,
  "recordNumber": 3900,
  "signVisualComposition": null,
  "activeHandshape": 13.1,
  "passiveHandshape": 5.3,
  "primaryLocation": 15,
  "secondLocation": 25,
  "antonyms": [],
  "synonyms": [],
  "interjection": [],
  "particleLexeme": [],
  "verbLexeme": [
    "1. To take someone's fingerprints by pressing their fingers on to an inky pad and then on to paper, so that you can see what their fingerprints look like. English = fingerprint."
  ],
  "questionLexeme": [],
  "generalMeaning": null,
  "nominalLexeme": [
    "1. A mark made by your finger that shows the lines on your skin. English = fingerprint."
  ],
  "idGloss": "fingerprint",
  "oldEntry": "Popular explanation: making a fingerprint.",
  "seeAlso": []
}
