{
  "tags": [
    "nomlex1",
    "gensign",
    "doublehnd",
    "domonly",
    "engtf1",
    "engtf2",
    "engtf3",
    "engtf4",
    "engtf5",
    "engtf6",
    "cf1",
    "cf2"
  ],
  "sense": "",
  "blend": "",
  "queries": "",
  "genmean": "Something with an opening and closing lid, such as a lap top computer, portable compact TTY, or pencil case, or any thing or any action directly or indirectly associated with this, especially a folder.",
  "questlex": [],
  "idgloss": "folder",
  "oldentry": "",
  "english": [
    "folder",
    "lap-top computer",
    "portable TTY",
    "compact TTY",
    "TTY",
    "pencil case"
  ],
  "deictic": [],
  "verblex": [],
  "cf": [
    "folder.open",
    "folder.close"
  ],
  "interj": [],
  "partlex": [],
  "nomlex": [
    "1. A thin piece of cardboard folded into the shape of a container or cover, in which you can keep documents. English = folder."
  ],
  "signNumber": 4150,
  "recordNumber": 2504,
  "signVisualComposition": "",
  "activeHandShape": 5.3,
  "passiveHandShape": 5.3,
  "primaryLocation": 15,
  "secondLocation": 26,
  "antonyms": [],
  "synonyms": []
}
