{
  "tags": [
    "nomlex1",
    "auslex",
    "doublehnd",
    "domonly",
    "engtf1",
    "engtf2",
    "engtf3",
    "cf1",
    "cf2",
    "cf3"
  ],
  "sense": "2",
  "blend": null,
  "queries": null,
  "english": [
    "stitch",
    "plain stitch",
    "garter stitch"
  ],
  "deictic": [],
  "signNumber": 1008,
  "recordNumber": 587,
  "signVisualComposition": null,
  "activeHandshape": 1.1,
  "passiveHandshape": 1.1,
  "primaryLocation": 15,
  "secondLocation": 26,
  "antonyms": [],
  "synonyms": [],
  "interjection": [],
  "particleLexeme": [],
  "verbLexeme": [],
  "questionLexeme": [],
  "generalMeaning": null,
  "nominalLexeme": [
    "1. In knitting, a simple, plain stitch. English = plain stitch, garter stitch."
  ],
  "idGloss": "garter",
  "oldEntry": null,
  "seeAlso": [
    "crochet",
    "knit.1a",
    "purl"
  ]
}
