{
  "tags": [
    "verblex1",
    "auslex",
    "doublehnd",
    "sym",
    "para",
    "engtf1",
    "engtf2",
    "ant1"
  ],
  "sense": null,
  "blend": null,
  "queries": null,
  "english": [
    "lift",
    "elevator"
  ],
  "deictic": [],
  "signNumber": 3887,
  "recordNumber": 2313,
  "signVisualComposition": null,
  "activeHandshape": 5.3,
  "passiveHandshape": 5.3,
  "primaryLocation": 15,
  "secondLocation": 25,
  "antonyms": [
    "go.up.in.lift"
  ],
  "synonyms": [],
  "interjection": [],
  "particleLexeme": [],
  "verbLexeme": [
    "1. To descend in a lift."
  ],
  "questionLexeme": [],
  "generalMeaning": null,
  "nominalLexeme": [],
  "idGloss": "go.down.in.lift",
  "oldEntry": null,
  "seeAlso": [
    "lift.3a"
  ]
}
