{
  "tags": [
    "verblex1",
    "reglex",
    "wa",
    "sa",
    "colors",
    "twohand",
    "domonly",
    "engtf1",
    "engtf2",
    "syn1",
    "syn2",
    "syn3"
  ],
  "sense": null,
  "blend": null,
  "queries": null,
  "english": [
    "grey",
    "gray"
  ],
  "deictic": [],
  "signNumber": 5043,
  "recordNumber": 3042,
  "signVisualComposition": null,
  "activeHandshape": 6.2,
  "passiveHandshape": 5.3,
  "primaryLocation": 15,
  "secondLocation": 24,
  "antonyms": [],
  "synonyms": [
    "grey.1",
    "grey.2",
    "grey.3"
  ],
  "interjection": [],
  "particleLexeme": [],
  "verbLexeme": [
    "1. To be the colour of ashes or clouds on a rainy day. English = (be) grey, (be) gray."
  ],
  "questionLexeme": [],
  "generalMeaning": null,
  "nominalLexeme": [],
  "idGloss": "grey.4",
  "oldEntry": null,
  "seeAlso": []
}
