{
  "tags": [
    "nomlex1",
    "verblex1",
    "auslex",
    "mindact",
    "onehand",
    "engtf1",
    "engtf2",
    "syn1",
    "syn2"
  ],
  "sense": "",
  "blend": "",
  "queries": "",
  "english": [
    "imagination",
    "imagine"
  ],
  "deictic": [],
  "cf": [],
  "signNumber": 500,
  "recordNumber": 278,
  "signVisualComposition": "",
  "activeHandShape": 1.1,
  "passiveHandShape": 0,
  "primaryLocation": 3,
  "secondLocation": null,
  "antonyms": [],
  "synonyms": [
    "imagine.1a",
    "imagine.2"
  ],
  "interjection": [],
  "particleLexeme": [],
  "verbLexeme": [
    "1. To form a picture of idea of something in your mind. English = imagine."
  ],
  "questionLexeme": [],
  "genitiveClassifiers": "",
  "nominalLexeme": [
    "1. The ability that you have to form ideas of new or exciting things; the part of your mind which you use to form pictures or ideas of things that do not necessarily exist in real life. English = imagination."
  ],
  "idGloss": "imagination.1a",
  "oldEntry": ""
}
