{
  "tags": [
    "nomlex1",
    "verblex1",
    "auslex",
    "travel",
    "doublehnd",
    "alternate",
    "sym",
    "para",
    "engtf1",
    "cf1",
    "syn1"
  ],
  "sense": "1",
  "blend": null,
  "queries": null,
  "english": [
    "journey"
  ],
  "deictic": [],
  "signNumber": 1088,
  "recordNumber": 638,
  "signVisualComposition": null,
  "activeHandshape": 1.1,
  "passiveHandshape": 1.1,
  "primaryLocation": 15,
  "secondLocation": 26,
  "antonyms": [],
  "synonyms": [],
  "interjection": [],
  "particleLexeme": [],
  "verbLexeme": [
    "1. To travel a long way from one place to another, usually in a leisurely or roundabout way. English = journey, go on a journey, go on a trip."
  ],
  "questionLexeme": [],
  "generalMeaning": null,
  "nominalLexeme": [
    "1. A long leisurely or roundabout journey or trip."
  ],
  "idGloss": "journey.1a",
  "oldEntry": null,
  "seeAlso": [
    "wander"
  ]
}
