{
  "tags": [
    "nomlex1",
    "nomlex2",
    "nomlex3",
    "nomlex4",
    "verblex1",
    "gensign",
    "twohand",
    "domonly",
    "obscure",
    "engtf1",
    "engtf2",
    "engtf3",
    "engtf4",
    "syn1"
  ],
  "sense": "",
  "blend": "",
  "queries": "",
  "english": [
    "knob",
    "stone",
    "berry",
    "bead"
  ],
  "deictic": [],
  "cf": [
    "tomato.2a"
  ],
  "signNumber": 199,
  "recordNumber": 115,
  "signVisualComposition": "",
  "activeHandShape": 0.1,
  "passiveHandShape": 1.1,
  "primaryLocation": 15,
  "secondLocation": 27,
  "antonyms": [],
  "synonyms": [
    "beads.1a"
  ],
  "interjection": [],
  "particleLexeme": [],
  "verbLexeme": [
    "1. To use a piece of chalk to dust the end of a snooker cue, to chalk the cue."
  ],
  "questionLexeme": [],
  "genitiveClassifiers": "Any thing which is long and thin with a small sphere-like protrusion at one end, or any thing or any action that is directly or indirectly associated with this, such as a knob or berry, or the action of chalking a snooker cue.",
  "nominalLexeme": [
    "1. A rounded lump on the end of a stick or post. English = knob.",
    "2. A small piece of rock. English = stone.",
    "3. A kind of small, round fruit that grows on a bush or tree, some of which you can eat.  English = berry.",
    "4. A small piece of coloured glass, wood, or plastic with a hole through the middle. English = bead."
  ],
  "idGloss": "knob.1a",
  "oldEntry": "Popular explanation: something small and round at the end of something long and thin."
}
