{
  "tags": [
    "verblex1",
    "auslex",
    "twohand",
    "domonly",
    "transl",
    "engtf1",
    "engtf2",
    "cf1",
    "syn1"
  ],
  "sense": "",
  "blend": "",
  "queries": "",
  "genmean": "",
  "questlex": [],
  "idgloss": "lean.1a",
  "oldentry": "Popular explanation: moving the head to one side.",
  "english": [
    "lean",
    "tilt"
  ],
  "deictic": [],
  "verblex": [
    "1. To move your head, or head and body, to one side; to tilt your head; to lean."
  ],
  "cf": [
    "bow.1a"
  ],
  "interj": [],
  "partlex": [],
  "nomlex": [],
  "signNumber": 5947,
  "recordNumber": 3542,
  "signVisualComposition": "",
  "activeHandShape": 10.1,
  "passiveHandShape": 1.1,
  "primaryLocation": 14,
  "secondLocation": 27,
  "antonyms": [],
  "synonyms": []
}
