{
  "tags": [
    "nomlex1",
    "verblex1",
    "auslex",
    "animal",
    "onehand",
    "obscure",
    "engtf1",
    "cf1",
    "cf2"
  ],
  "sense": "",
  "blend": "",
  "queries": "",
  "genmean": "",
  "questlex": [],
  "idgloss": "lizard",
  "oldentry": "Popular explanation: the tongue of a lizard.",
  "english": [
    "lizard"
  ],
  "deictic": [],
  "verblex": [
    "1. Of a lizard, to flick out the tongue."
  ],
  "cf": [
    "snake",
    "spiteful"
  ],
  "interj": [],
  "partlex": [],
  "nomlex": [
    "1. A small animal with short legs, a long tail, and a rough dry skin. English = lizard."
  ],
  "signNumber": 6374,
  "recordNumber": 3810,
  "signVisualComposition": "",
  "activeHandShape": 11.1,
  "passiveHandShape": 0,
  "primaryLocation": 11,
  "secondLocation": null,
  "antonyms": [],
  "synonyms": []
}
