{
  "tags": [
    "nomlex1",
    "verblex1",
    "orient",
    "auslex",
    "quantity",
    "doublehnd",
    "sym",
    "engtf1",
    "engtf2",
    "cf1",
    "syn1",
    "syn2"
  ],
  "sense": "1",
  "blend": "",
  "queries": "",
  "english": [
    "length",
    "long"
  ],
  "deictic": [],
  "cf": [
    "factory.2"
  ],
  "signNumber": 4843,
  "recordNumber": 2926,
  "signVisualComposition": "",
  "activeHandshape": 6.1,
  "passiveHandshape": 6.1,
  "primaryLocation": 15,
  "secondLocation": 25,
  "antonyms": [],
  "synonyms": [
    "broad.1a",
    "wide"
  ],
  "interjection": [],
  "particleLexeme": [],
  "verbLexeme": [
    "1. To measure a great distance (relative to other things of its type) from one end to the other. English = (be) long."
  ],
  "questionLexeme": [],
  "generalMeaning": "",
  "nominalLexeme": [
    "1. The large horizontal distance measured from one end of a thing to the other. English = length."
  ],
  "idGloss": "long",
  "oldEntry": ""
}
