{
  "tags": [
    "nomlex1",
    "nomlex2",
    "nomlex3",
    "verblex1",
    "verblex2",
    "verblex3",
    "auslex",
    "doublehnd",
    "sym",
    "para",
    "law",
    "engtf1",
    "engtf2",
    "engtf3",
    "engtf4",
    "engtf5",
    "engtf6",
    "syn1"
  ],
  "sense": "",
  "blend": "",
  "queries": "",
  "genmean": "",
  "questlex": [],
  "idgloss": "murder.2",
  "oldentry": "",
  "english": [
    "murder",
    "strangulation",
    "throttle",
    "strangle",
    "choke",
    "murderer"
  ],
  "deictic": [],
  "verblex": [
    "1. To deliberately and unlawfully kill someone. English = murder.",
    "2. To hold someone tightly by the throat so that they cannot breath, usually in order to kill them. English = throttle.",
    "3. To kill someone by squeezing their throat. English = strangle, choke."
  ],
  "cf": [],
  "interj": [],
  "partlex": [],
  "nomlex": [
    "1. The deliberate and unlawful killing of a person. English = murder.",
    "2. The act of killing someone by squeezing their throat. English = strangulation",
    "3. A person who deliberately and unlawfully kills someone. English = murderer."
  ],
  "signNumber": 4610,
  "recordNumber": 2791,
  "signVisualComposition": "",
  "activeHandShape": 5.5,
  "passiveHandShape": 5.5,
  "primaryLocation": 14,
  "secondLocation": 25,
  "antonyms": [],
  "synonyms": [
    "murder.1"
  ]
}
