{
  "tags": [
    "nomlex1",
    "verblex1",
    "interj1",
    "interj2",
    "auslex",
    "onehand",
    "engtf1",
    "engtf2",
    "engtf3",
    "engtf4",
    "engtf5",
    "engtf6",
    "ant1",
    "cf1"
  ],
  "sense": "",
  "blend": "",
  "queries": "",
  "english": [
    "trifle",
    "triviality",
    "nothing",
    "trivial",
    "trifling",
    "insignificant"
  ],
  "deictic": [],
  "cf": [
    "O.1"
  ],
  "signNumber": 308,
  "recordNumber": 175,
  "signVisualComposition": "",
  "activeHandshape": 0.2,
  "passiveHandshape": 0,
  "primaryLocation": 14,
  "secondLocation": null,
  "antonyms": [
    "some.1a"
  ],
  "synonyms": [],
  "interjection": [
    "1. Used alone in response from your addressee to repeat something you have said to mean that you won't bother because what you said was not very important. English = 'It's nothing!', 'Forget it!', and so on.",
    "2. Used alone to deny that you have done or said something. English = 'I haven't done a thing!', 'I've done nothing!', 'I didn't say anything at all!', and so on."
  ],
  "particleLexeme": [],
  "verbLexeme": [
    "1. To be very unimportant and not worth attention. English = (be) nothing, (be) trivial, (be) trifling, (be) insignificant.",
    "2. To do nothing at all, usually because you are lazy or uninterested."
  ],
  "questionLexeme": [],
  "generalMeaning": "",
  "nominalLexeme": [
    "1. Something which is not very important. English = trifle, triviality."
  ],
  "idGloss": "nothing.1a",
  "oldEntry": ""
}
