{
  "tags": [
    "verblex1",
    "interj1",
    "reglex",
    "vic",
    "onehand",
    "engtf1",
    "engtf2",
    "syn1"
  ],
  "sense": "",
  "blend": "",
  "queries": "",
  "english": [
    "boo-boo",
    "oops"
  ],
  "deictic": [],
  "cf": [],
  "signNumber": 246,
  "recordNumber": 143,
  "signVisualComposition": "",
  "activeHandshape": 0.2,
  "passiveHandshape": 0,
  "primaryLocation": 2,
  "secondLocation": null,
  "antonyms": [],
  "synonyms": [],
  "interjection": [
    "1. Used alone to indicate that there has been a slight accident or mistake. English = 'Oops!'"
  ],
  "particleLexeme": [],
  "verbLexeme": [
    "1. To make a slight mistake, especially overlooking or forgetting something. Idiomatic English = boo-boo, make a boo-boo."
  ],
  "questionLexeme": [],
  "generalMeaning": "",
  "nominalLexeme": [],
  "idGloss": "oops",
  "oldEntry": ""
}
