{
  "tags": [
    "nomlex1",
    "comp",
    "auslex",
    "drinks",
    "onehand",
    "obscure",
    "engtf1",
    "cf1"
  ],
  "sense": "",
  "blend": "",
  "queries": "",
  "english": [
    "orange juice"
  ],
  "deictic": [],
  "cf": [
    "orange"
  ],
  "signNumber": 45,
  "recordNumber": 27,
  "signVisualComposition": "ORANGE + J",
  "activeHandshape": 0.1,
  "passiveHandshape": 0,
  "primaryLocation": 9,
  "secondLocation": null,
  "antonyms": [],
  "synonyms": [],
  "interjection": [],
  "particleLexeme": [],
  "verbLexeme": [],
  "questionLexeme": [],
  "generalMeaning": "",
  "nominalLexeme": [
    "1. A drink made from squeezed oranges. English = orange juice."
  ],
  "idGloss": "orange juice",
  "oldEntry": "Popular explanation: 'orange' + the letter 'j'."
}
