{
  "tags": [
    "nomlex1",
    "nomlex2",
    "auslex",
    "sports",
    "doublehnd",
    "sym",
    "engtf1"
  ],
  "sense": null,
  "blend": null,
  "queries": null,
  "english": [
    "over"
  ],
  "deictic": [],
  "signNumber": 3878,
  "recordNumber": 2306,
  "signVisualComposition": null,
  "activeHandshape": 5.3,
  "passiveHandshape": 5.3,
  "primaryLocation": 15,
  "secondLocation": 24,
  "antonyms": [],
  "synonyms": [],
  "interjection": [],
  "particleLexeme": [],
  "verbLexeme": [],
  "questionLexeme": [],
  "generalMeaning": null,
  "nominalLexeme": [
    "1. In cricket, the number of balls delivered between successive changes of bowlers. English = over.",
    "2. In cricket, the part of the game played between successive changes of bowlers. English = over."
  ],
  "idGloss": "over.in.cricket",
  "oldEntry": null,
  "seeAlso": []
}
