{
  "tags": [
    "nomlex1",
    "verblex1",
    "reglex",
    "nsw",
    "money",
    "shop",
    "onehand",
    "opaque",
    "engtf1",
    "engtf2"
  ],
  "sense": "2",
  "blend": null,
  "queries": null,
  "english": [
    "debt",
    "owe"
  ],
  "deictic": [],
  "signNumber": 3295,
  "recordNumber": 1923,
  "signVisualComposition": null,
  "activeHandshape": 5.3,
  "passiveHandshape": 0,
  "primaryLocation": 11,
  "secondLocation": 0,
  "antonyms": [],
  "synonyms": [],
  "interjection": [],
  "particleLexeme": [],
  "verbLexeme": [
    "1. To have the obligation to give money which you have borrowed from someone back to them. English = owe, (be) in debt to."
  ],
  "questionLexeme": [],
  "generalMeaning": null,
  "nominalLexeme": [
    "1. The amount of money which you have borrowed from someone but have not yet paid them back. English = debt."
  ],
  "idGloss": "owe.1",
  "oldEntry": null,
  "seeAlso": []
}
