{
  "tags": [
    "nomlex1",
    "auslex",
    "twohand",
    "domonly",
    "aslloan",
    "engtf1",
    "engtf2",
    "engtf3"
  ],
  "sense": "",
  "blend": "",
  "queries": "",
  "genmean": "",
  "questlex": [],
  "idgloss": "part.1a",
  "oldentry": "",
  "english": [
    "part",
    "piece",
    "portion"
  ],
  "deictic": [],
  "verblex": [],
  "cf": [
    "separate"
  ],
  "interj": [],
  "partlex": [],
  "nomlex": [
    "1. One of the pieces or areas that another thing consists of. English = part, piece, portion."
  ],
  "signNumber": 1870,
  "recordNumber": 1120,
  "signVisualComposition": "",
  "activeHandShape": 2.3,
  "passiveHandShape": 5.3,
  "primaryLocation": 15,
  "secondLocation": 25,
  "antonyms": [],
  "synonyms": []
}
