{
  "tags": [
    "nomlex1",
    "verblex1",
    "bodyloc",
    "auslex",
    "onehand",
    "engtf1",
    "cf1",
    "syn1"
  ],
  "sense": "",
  "blend": "",
  "queries": "",
  "english": [
    "pat"
  ],
  "deictic": [],
  "cf": [
    "shoulder.1a"
  ],
  "signNumber": 3319,
  "recordNumber": 1940,
  "signVisualComposition": "",
  "activeHandShape": 5.3,
  "passiveHandShape": 0,
  "primaryLocation": 13,
  "secondLocation": null,
  "antonyms": [],
  "synonyms": [],
  "interjection": [],
  "particleLexeme": [],
  "verbLexeme": [
    "1. To tap or hit something lightly, usually with your fingers. English = pat."
  ],
  "questionLexeme": [],
  "genitiveClassifiers": "The action of tapping or hitting something with you hand, such as a part of your body, the back of your other hand or some other object, or any action or thing directly or indirectly associated with this.",
  "nominalLexeme": [
    "1. A light tap on something lightly, usually with your fingers. English = pat."
  ],
  "idGloss": "pat.1a",
  "oldEntry": ""
}
