{
  "tags": [
    "nomlex1",
    "verblex1",
    "dir",
    "bodyloc",
    "auslex",
    "onehand",
    "transl",
    "engtf1",
    "engtf2"
  ],
  "sense": null,
  "blend": null,
  "queries": null,
  "english": [
    "pinch",
    "tweak"
  ],
  "deictic": [],
  "signNumber": 2527,
  "recordNumber": 1404,
  "signVisualComposition": null,
  "activeHandshape": 5.1,
  "passiveHandshape": 0,
  "primaryLocation": 15,
  "secondLocation": null,
  "antonyms": [],
  "synonyms": [],
  "interjection": [],
  "particleLexeme": [],
  "verbLexeme": [
    "1. To squeeze a part of someone's body between your thumb and first finger. English = pinch, tweak."
  ],
  "questionLexeme": [],
  "generalMeaning": null,
  "nominalLexeme": [
    "1. The grabbing or squeezing of a part of someone's body between your thumb and first finger. English = pinch, tweak."
  ],
  "idGloss": "pinch",
  "oldEntry": "Popular explanation: pinching something.",
  "seeAlso": []
}
