{
  "tags": [
    "interj1",
    "auslex",
    "onehand",
    "engtf1"
  ],
  "sense": "",
  "blend": "",
  "queries": "",
  "english": [
    "piss off"
  ],
  "deictic": [],
  "cf": [],
  "signNumber": 343,
  "recordNumber": 189,
  "signVisualComposition": "",
  "activeHandshape": 0.2,
  "passiveHandshape": 0,
  "primaryLocation": 15,
  "secondLocation": null,
  "antonyms": [],
  "synonyms": [],
  "interjection": [
    "1. Used to tell someone in a rude way that you want them to go away. Informal English = 'Piss off!'"
  ],
  "particleLexeme": [],
  "verbLexeme": [],
  "questionLexeme": [],
  "generalMeaning": "",
  "nominalLexeme": [],
  "idGloss": "piss.off.2",
  "oldEntry": ""
}
