{
  "tags": [
    "nomlex1",
    "verblex1",
    "orient",
    "auslex",
    "bodyact",
    "doublehnd",
    "sym",
    "para",
    "obscure",
    "engtf1",
    "cf1",
    "syn1"
  ],
  "sense": "",
  "blend": "",
  "queries": "",
  "english": [
    "rest"
  ],
  "deictic": [],
  "cf": [
    "lie.down"
  ],
  "signNumber": 1647,
  "recordNumber": 978,
  "signVisualComposition": "",
  "activeHandshape": 2.1,
  "passiveHandshape": 2.1,
  "primaryLocation": 14,
  "secondLocation": 25,
  "antonyms": [],
  "synonyms": [
    "relax.1"
  ],
  "interjection": [],
  "particleLexeme": [],
  "verbLexeme": [
    "1. To not do anything active, especially by sitting or lying quietly, for a period of time. English = rest. Idiomatic English = put one's feet up."
  ],
  "questionLexeme": [],
  "generalMeaning": "",
  "nominalLexeme": [
    "1. A period of time in which you are not doing anything active. English = rest."
  ],
  "idGloss": "rest.1a",
  "oldEntry": "Popular explanation: putting one's legs up."
}
