{
  "tags": [
    "nomlex1",
    "nomlex2",
    "verblex1",
    "verblex2",
    "verblex3",
    "auslex",
    "onehand",
    "engtf1",
    "engtf2",
    "engtf3",
    "engtf4"
  ],
  "sense": null,
  "blend": null,
  "queries": "This sign can also be made with a subordinate Flat or Point hand as a point of reference.",
  "english": [
    "rid",
    "toss out",
    "sell off",
    "reject"
  ],
  "deictic": [],
  "signNumber": 6345.1,
  "recordNumber": 3789,
  "signVisualComposition": null,
  "activeHandshape": 11.1,
  "passiveHandshape": 0,
  "primaryLocation": 8,
  "secondLocation": 0,
  "antonyms": [],
  "synonyms": [],
  "interjection": [],
  "particleLexeme": [],
  "verbLexeme": [
    "1. To take action so that you no longer have something you do not want. English = toss out, get rid of, rid yourself of.",
    "2. To sell something that you no longer want. English = sell off.",
    "3. To get rid of or not accept something because it is not wanted or is not good enough, especially a product because something is wrong with it. English = reject."
  ],
  "questionLexeme": [],
  "generalMeaning": null,
  "nominalLexeme": [
    "1. Things that you no longer want and have thrown away or plan to throw away.",
    "2. Something which is not accepted, especially a product because something is wrong with it. English = reject."
  ],
  "idGloss": "rid",
  "oldEntry": null,
  "seeAlso": []
}
