{
  "tags": [
    "nomlex1",
    "auslex",
    "foods",
    "doublehnd",
    "sym",
    "engtf1"
  ],
  "sense": null,
  "blend": null,
  "queries": null,
  "english": [
    "sausage"
  ],
  "deictic": [],
  "signNumber": 5217,
  "recordNumber": 3134,
  "signVisualComposition": null,
  "activeHandshape": 7.1,
  "passiveHandshape": 7.1,
  "primaryLocation": 14,
  "secondLocation": 27,
  "antonyms": [],
  "synonyms": [],
  "interjection": [],
  "particleLexeme": [],
  "verbLexeme": [],
  "questionLexeme": [],
  "generalMeaning": null,
  "nominalLexeme": [
    "1. A tube-shaped piece of finely minced meat which is mixed with other ingredients and put into a thin casing; or a string of them. English = sausage; sausages."
  ],
  "idGloss": "sausage.1a",
  "oldEntry": null,
  "seeAlso": []
}
