{
  "tags": [
    "verblex1",
    "verblex2",
    "verblex3",
    "interj1",
    "interj2",
    "enddir",
    "auslex",
    "senseact",
    "onehand",
    "transl",
    "engtf1",
    "engtf2",
    "engtf3",
    "syn1",
    "syn2",
    "syn3"
  ],
  "sense": "",
  "blend": "",
  "queries": "",
  "english": [
    "see",
    "visit",
    "understand"
  ],
  "deictic": [],
  "cf": [],
  "signNumber": 551,
  "recordNumber": 316,
  "signVisualComposition": "",
  "activeHandShape": 1.1,
  "passiveHandShape": 0,
  "primaryLocation": 7,
  "secondLocation": null,
  "antonyms": [],
  "synonyms": [
    "look.at.1a",
    "visit.1",
    "vision"
  ],
  "interjection": [
    "1. Used alone to tell your addressee you understand what they mean. English = 'I see!'",
    "2. Used alone to tell your addressee that they should now be aware that what you said before was right because something has just happened that proves you were right. English = 'You see!'"
  ],
  "particleLexeme": [],
  "verbLexeme": [
    "1. To notice something with your eyes. English = see.",
    "2. To go and see someone and spend some time with them. English = see, visit.",
    "3. To understand what someone means or to understand why something happens. English = see, understand."
  ],
  "questionLexeme": [],
  "genitiveClassifiers": "",
  "nominalLexeme": [],
  "idGloss": "see.1a",
  "oldEntry": "Popular explanation: from the eye."
}
