{
  "tags": [
    "nomlex1",
    "verblex1",
    "auslex",
    "people",
    "onehand",
    "engtf1",
    "ant1",
    "cf1",
    "cf2"
  ],
  "sense": "",
  "blend": "",
  "queries": "",
  "english": [
    "short-hair"
  ],
  "deictic": [],
  "cf": [
    "curly",
    "curl.1a"
  ],
  "signNumber": 3195,
  "recordNumber": 1855,
  "signVisualComposition": "",
  "activeHandshape": 5.3,
  "passiveHandshape": 0,
  "primaryLocation": 8,
  "secondLocation": null,
  "antonyms": [
    "long-hair"
  ],
  "synonyms": [],
  "interjection": [],
  "particleLexeme": [],
  "verbLexeme": [
    "1. To have short hair."
  ],
  "questionLexeme": [],
  "generalMeaning": "",
  "nominalLexeme": [
    "1. Hair which is worn short."
  ],
  "idGloss": "short-hair",
  "oldEntry": ""
}
