{
  "tags": [
    "nomlex1",
    "nomlex2",
    "nomlex3",
    "auslex",
    "health",
    "family",
    "work",
    "onehand",
    "opaque",
    "engtf1",
    "ant1",
    "cf1",
    "cf2",
    "cf3"
  ],
  "sense": null,
  "blend": null,
  "queries": null,
  "english": [
    "sister"
  ],
  "deictic": [],
  "signNumber": 1363,
  "recordNumber": 805,
  "signVisualComposition": null,
  "activeHandshape": 1.2,
  "passiveHandshape": 0,
  "primaryLocation": 5,
  "secondLocation": null,
  "antonyms": [
    "brother.1a"
  ],
  "synonyms": [],
  "interjection": [],
  "particleLexeme": [],
  "verbLexeme": [],
  "questionLexeme": [],
  "generalMeaning": null,
  "nominalLexeme": [
    "1. A girl or a woman who has the same parents as you. English = sister.",
    "2. A woman who is a member of a religious order. English = sister.",
    "3. A senior nurse who supervises a hospital ward. English = sister."
  ],
  "idGloss": "sister",
  "oldEntry": null,
  "seeAlso": [
    "nurse.1",
    "nurse.2",
    "nurse.3a"
  ]
}
