{
  "tags": [
    "nomlex1",
    "nomlex2",
    "verblex1",
    "auslex",
    "onehand",
    "transl",
    "engtf1",
    "engtf2",
    "engtf3",
    "syn1"
  ],
  "sense": "2",
  "blend": "",
  "queries": "",
  "genmean": "",
  "questlex": [],
  "idgloss": "slave.1a",
  "oldentry": "Popular explanation: pulling on something around the neck.",
  "english": [
    "slave",
    "slavery",
    "enslave"
  ],
  "deictic": [],
  "verblex": [
    "1. To make someone a slave. English = enslave."
  ],
  "cf": [],
  "interj": [],
  "partlex": [],
  "nomlex": [
    "1. A person who is the property of another person and has to work for that person. English = slave.",
    "2. A system by which people are owned by other people for whom they have to work. English = slavery."
  ],
  "signNumber": 5632,
  "recordNumber": 3337,
  "signVisualComposition": "",
  "activeHandShape": 10.1,
  "passiveHandShape": 0,
  "primaryLocation": 12,
  "secondLocation": null,
  "antonyms": [],
  "synonyms": []
}
