{
  "tags": [
    "nomlex1",
    "nomlex2",
    "verblex1",
    "restrict",
    "twohand",
    "domonly",
    "engtf1",
    "engtf2",
    "engtf3",
    "engtf4",
    "engtf5",
    "syn1",
    "syn2"
  ],
  "sense": null,
  "blend": null,
  "queries": null,
  "english": [
    "marijuana",
    "hashish",
    "dope",
    "smoke",
    "hash"
  ],
  "deictic": [],
  "signNumber": 6273,
  "recordNumber": 3748,
  "signVisualComposition": null,
  "activeHandshape": 10.2,
  "passiveHandshape": 15.1,
  "primaryLocation": 10,
  "secondLocation": 27,
  "antonyms": [],
  "synonyms": [
    "smoke.dope.1",
    "pipe.3"
  ],
  "interjection": [],
  "particleLexeme": [],
  "verbLexeme": [
    "1. To smoke marijuana or hashish using a pipe; to smoke dope."
  ],
  "questionLexeme": [],
  "generalMeaning": null,
  "nominalLexeme": [
    "1. A small pipe used for smoking marijuana or hashish.",
    "2. A drug made from the hemp plant which people usually smoke like a cigarette or like tobacco in a pipe to make them feel relaxed. It is illegal in many countries. English = marijuana, hashish. Informal English = dope, hash."
  ],
  "idGloss": "smoke.dope.2",
  "oldEntry": null,
  "seeAlso": [
    "hash"
  ]
}
