{
  "tags": [
    "nomlex1",
    "marginal",
    "doublehnd",
    "sym",
    "para",
    "aslloan",
    "engtf1",
    "cf1",
    "cf2",
    "syn1"
  ],
  "sense": "",
  "blend": "",
  "queries": "",
  "genmean": "",
  "questlex": [],
  "idgloss": "strategy",
  "oldentry": "",
  "english": [
    "strategy"
  ],
  "deictic": [],
  "verblex": [],
  "cf": [
    "way",
    "road"
  ],
  "interj": [],
  "partlex": [],
  "nomlex": [
    "1. A plan you use in order to achieve something. English = strategy."
  ],
  "signNumber": 5902,
  "recordNumber": 3508,
  "signVisualComposition": "",
  "activeHandShape": 10.1,
  "passiveHandShape": 10.1,
  "primaryLocation": 15,
  "secondLocation": 25,
  "antonyms": [],
  "synonyms": []
}
