{
  "tags": [
    "nomlex1",
    "verblex1",
    "verblex2",
    "comp",
    "auslex",
    "lingact",
    "onehand",
    "engtf1",
    "engtf2",
    "syn1",
    "syn2"
  ],
  "sense": "",
  "blend": "",
  "queries": "",
  "english": [
    "suggestion",
    "suggest"
  ],
  "deictic": [],
  "cf": [],
  "signNumber": 6638,
  "recordNumber": 3952,
  "signVisualComposition": "THINK + PERHAPS",
  "activeHandshape": 16.1,
  "passiveHandshape": 0,
  "primaryLocation": 3,
  "secondLocation": null,
  "antonyms": [],
  "synonyms": [
    "idea.1a"
  ],
  "interjection": [],
  "particleLexeme": [],
  "verbLexeme": [
    "1. To put forward a plan or idea for someone to think about. English = suggest.",
    "2. To think that something may be possible."
  ],
  "questionLexeme": [],
  "generalMeaning": "",
  "nominalLexeme": [
    "1. The act of putting forward a plan or idea for someone to think about. English = suggestion."
  ],
  "idGloss": "suggest.2a",
  "oldEntry": ""
}
