{
  "tags": [
    "nomlex1",
    "restrict",
    "doublehnd",
    "alternate",
    "sym",
    "telecommun",
    "engtf1",
    "cf1"
  ],
  "sense": "",
  "blend": "",
  "queries": "",
  "genmean": "",
  "questlex": [],
  "idgloss": "telecommunications",
  "oldentry": "",
  "english": [
    "telecommunications"
  ],
  "deictic": [],
  "verblex": [],
  "cf": [
    "communicate.1a"
  ],
  "interj": [],
  "partlex": [],
  "nomlex": [
    "1. The science and activity of sending signals and messages over long distances using electronic equipment, particularly telephones. English = telecommunications."
  ],
  "signNumber": 6623,
  "recordNumber": 3941,
  "signVisualComposition": "",
  "activeHandShape": 15.1,
  "passiveHandShape": 15.1,
  "primaryLocation": 15,
  "secondLocation": 27,
  "antonyms": [],
  "synonyms": []
}
