{
  "tags": [
    "nomlex1",
    "reglex",
    "nth",
    "onehand",
    "law",
    "engtf1",
    "syn2"
  ],
  "sense": "",
  "blend": "",
  "queries": "",
  "english": [
    "thief"
  ],
  "deictic": [],
  "cf": [],
  "signNumber": 3479,
  "recordNumber": 2032,
  "signVisualComposition": "",
  "activeHandshape": 5.3,
  "passiveHandshape": 0,
  "primaryLocation": 15,
  "secondLocation": null,
  "antonyms": [],
  "synonyms": [
    "thief.1a"
  ],
  "interjection": [],
  "particleLexeme": [],
  "verbLexeme": [],
  "questionLexeme": [],
  "generalMeaning": "",
  "nominalLexeme": [
    "1. A person who takes something from another person, especially without using violence. English = thief."
  ],
  "idGloss": "thief.2",
  "oldEntry": ""
}
