{
  "tags": [
    "nomlex1",
    "verblex1",
    "orient",
    "auslex",
    "autos",
    "travel",
    "doublehnd",
    "domonly",
    "obscure",
    "engtf1",
    "syn1"
  ],
  "sense": "",
  "blend": "",
  "queries": "",
  "english": [
    "trailer"
  ],
  "deictic": [],
  "cf": [],
  "signNumber": 4118,
  "recordNumber": 2477,
  "signVisualComposition": "",
  "activeHandshape": 5.3,
  "passiveHandshape": 5.3,
  "primaryLocation": 15,
  "secondLocation": 22,
  "antonyms": [],
  "synonyms": [
    "tow.1a"
  ],
  "interjection": [],
  "particleLexeme": [],
  "verbLexeme": [
    "1. To tow a trailer."
  ],
  "questionLexeme": [],
  "generalMeaning": "",
  "nominalLexeme": [
    "1. A vehicle like a cart which can be loaded with things and pulled behind a car. English = trailer."
  ],
  "idGloss": "trailer.1",
  "oldEntry": "Popular explanation: one vehicle attached to another."
}
