{
  "tags": [
    "nomlex1",
    "verblex1",
    "marginal",
    "onehand",
    "aslloan",
    "engtf1",
    "cf1",
    "cf2",
    "syn1",
    "syn2"
  ],
  "sense": "",
  "blend": "",
  "queries": "",
  "genmean": "",
  "questlex": [],
  "idgloss": "trust",
  "oldentry": "",
  "english": [
    "trust"
  ],
  "deictic": [],
  "verblex": [
    "1. To believe that someone is honest and would not deliberately do anything to harm you. English = trust."
  ],
  "cf": [
    "character",
    "attitude.1a"
  ],
  "interj": [],
  "partlex": [],
  "nomlex": [
    "1. The belief or feeling that someone is honest and would not deliberately do anything to harm you. English = trust."
  ],
  "signNumber": 6089,
  "recordNumber": 3622,
  "signVisualComposition": "",
  "activeHandShape": 10.2,
  "passiveHandShape": 0,
  "primaryLocation": 14,
  "secondLocation": null,
  "antonyms": [],
  "synonyms": [
    "believe.2a",
    "true"
  ]
}
