{
  "tags": [
    "nomlex1",
    "orient",
    "auslex",
    "nature",
    "doublehnd",
    "sym",
    "transl",
    "engtf1"
  ],
  "sense": "",
  "blend": "",
  "queries": "",
  "english": [
    "valley"
  ],
  "deictic": [],
  "cf": [],
  "signNumber": 3892,
  "recordNumber": 2316,
  "signVisualComposition": "",
  "activeHandshape": 5.3,
  "passiveHandshape": 5.3,
  "primaryLocation": 14,
  "secondLocation": 26,
  "antonyms": [],
  "synonyms": [],
  "interjection": [],
  "particleLexeme": [],
  "verbLexeme": [],
  "questionLexeme": [],
  "generalMeaning": "",
  "nominalLexeme": [
    "1. A long, narrow area of land between hills, especially one that has a river flowing through it. English = valley."
  ],
  "idGloss": "valley",
  "oldEntry": "Popular explanation: the outline of a valley."
}
