{
  "tags": [
    "verblex1",
    "auslex",
    "onehand",
    "engtf1"
  ],
  "sense": "",
  "blend": "",
  "queries": "",
  "english": [
    "wet the bed"
  ],
  "deictic": [],
  "cf": [],
  "signNumber": 3217,
  "recordNumber": 1869,
  "signVisualComposition": "",
  "activeHandshape": 5.3,
  "passiveHandshape": 0,
  "primaryLocation": 8,
  "secondLocation": null,
  "antonyms": [],
  "synonyms": [],
  "interjection": [],
  "particleLexeme": [],
  "verbLexeme": [
    "1. Of people, especially children, to urinate in your bed because you cannot control your bladder. Idiomatic English = wet the bed."
  ],
  "questionLexeme": [],
  "generalMeaning": "",
  "nominalLexeme": [],
  "idGloss": "wet.bed",
  "oldEntry": ""
}
