{
  "tags": [
    "nomlex1",
    "auslex",
    "doublehnd",
    "sym",
    "transl",
    "engtf1"
  ],
  "sense": null,
  "blend": null,
  "queries": null,
  "english": [
    "wheelchair"
  ],
  "deictic": [],
  "signNumber": 1108,
  "recordNumber": 651,
  "signVisualComposition": null,
  "activeHandshape": 1.1,
  "passiveHandshape": 1.1,
  "primaryLocation": 17,
  "secondLocation": null,
  "antonyms": [],
  "synonyms": [],
  "interjection": [],
  "particleLexeme": [],
  "verbLexeme": [],
  "questionLexeme": [],
  "generalMeaning": null,
  "nominalLexeme": [
    "1. A chair with wheels that ill or injured people use in order to move about, when they cannot walk. English = wheelchair."
  ],
  "idGloss": "wheelchair.1",
  "oldEntry": "Popular explanation: the outline of wheels of a wheel chair.",
  "seeAlso": []
}
