{
  "tags": [
    "nomlex1",
    "verblex1",
    "auslex",
    "onehand",
    "engtf1",
    "engtf2",
    "syn1"
  ],
  "sense": null,
  "blend": null,
  "queries": null,
  "english": [
    "wisdom",
    "wise"
  ],
  "deictic": [],
  "signNumber": 3134,
  "recordNumber": 1811,
  "signVisualComposition": null,
  "activeHandshape": 5.3,
  "passiveHandshape": 0,
  "primaryLocation": 2,
  "secondLocation": null,
  "antonyms": [],
  "synonyms": [
    "clever.1a"
  ],
  "interjection": [],
  "particleLexeme": [],
  "verbLexeme": [
    "1. To be able to use your experience and knowledge in order to make sensible decisions and judgements mostly because you are both old and intelligent. English = (be) wise."
  ],
  "questionLexeme": [],
  "generalMeaning": null,
  "nominalLexeme": [
    "1. The ability to use your experience and knowledge in order to make sensible decisions and judgements. English = wisdom"
  ],
  "idGloss": "wise",
  "oldEntry": null,
  "seeAlso": []
}
