{
  "tags": [
    "verblex1",
    "orient",
    "auslex",
    "lingact",
    "twohand",
    "domonly",
    "transl",
    "engtf1",
    "cf1",
    "cf2",
    "cf3"
  ],
  "sense": "",
  "blend": "",
  "queries": "",
  "english": [
    "write"
  ],
  "deictic": [],
  "cf": [
    "agenda",
    "list.1",
    "write.1a"
  ],
  "signNumber": 6452,
  "recordNumber": 3846,
  "signVisualComposition": "",
  "activeHandshape": 11.1,
  "passiveHandshape": 5.3,
  "primaryLocation": 14,
  "secondLocation": 25,
  "antonyms": [],
  "synonyms": [],
  "interjection": [],
  "particleLexeme": [],
  "verbLexeme": [
    "1. To write a list."
  ],
  "questionLexeme": [],
  "generalMeaning": "",
  "nominalLexeme": [],
  "idGloss": "write.list",
  "oldEntry": "Popular explanation: writing a list."
}
